squarewaveperiod.v
//This is fourth assignment from Udemy SV courseware. Task
//is to generate a squarewave with period of 40ns and duty
//cycle of 0.4. Phase difference with reference clock is 0.
//The term Duty Cycle refers to time for which signal rema-
//ins high.

`timescale 1ns/1ns;
module squareduty4;
  reg clk, duty;

  always #20 clk = ~clk;
  always
  begin
    #24 duty=1'b1;
    #16 duty=1'b0;
  end

  initial
  begin
    clk = 1'b0;
    duty = 1'b0;
  end
  
  initial
  begin
    $dumpfile("dutycycle.vcd");
    $dumpvars(0,squareduty4);
    #1000 $finish;
  end
endmodule

dutycycle.vcd
$date
	Wed Jul 19 08:37:10 2023
$end

$version
	Synopsys VCS version Q-2020.03-SP1-1_Full64
$end

$timescale
	1ns
$end

$comment Csum: 1 62495bc6933db575 $end


$scope module squareduty4 $end
$var reg 1 ! clk $end
$var reg 1 " duty $end
$upscope $end

$enddefinitions $end

#0
$dumpvars
0!
0"
$end
#20
1!
#24
1"
#40
0!
0"
#60
1!
#64
1"
#80
0!
0"
#100
1!
#104
1"
#120
0!
0"
#140
1!
#144
1"
#160
0!
0"
#180
1!
#184
1"
#200
0!
0"
#220
1!
#224
1"
#240
0!
0"
#260
1!
#264
1"
#280
0!
0"
#300
1!
#304
1"
#320
0!
0"
#340
1!
#344
1"
#360
0!
0"
#380
1!
#384
1"
#400
0!
0"
#420
1!
#424
1"
#440
0!
0"
#460
1!
#464
1"
#480
0!
0"
#500
1!
#504
1"
#520
0!
0"
#540
1!
#544
1"
#560
0!
0"
#580
1!
#584
1"
#600
0!
0"
#620
1!
#624
1"
#640
0!
0"
#660
1!
#664
1"
#680
0!
0"
#700
1!
#704
1"
#720
0!
0"
#740
1!
#744
1"
#760
0!
0"
#780
1!
#784
1"
#800
0!
0"
#820
1!
#824
1"
#840
0!
0"
#860
1!
#864
1"
#880
0!
0"
#900
1!
#904
1"
#920
0!
0"
#940
1!
#944
1"
#960
0!
0"
#980
1!
#984
1"
